gosms/__init__.py
gosms/exceptions.py
gosms/factories.py
gosms/request.py
gosms/settings.py
gosms/sms.py
gosmsge-1.0.5.dist-info/METADATA
gosmsge-1.0.5.dist-info/WHEEL
gosmsge-1.0.5.dist-info/top_level.txt
gosmsge-1.0.5.dist-info/RECORD
