Metadata-Version: 2.1
Name: gosmsge
Version: 1.0.5
Summary: Package for GoSMSGE that helps you to send messages to your clients
Home-page: UNKNOWN
Author: Graey
Author-email: info@graey.ge
License: MIT
Project-URL: Source, https://github.com/gosms-ge/gosmsge-python
Platform: UNKNOWN
Requires-Dist: requests (>=2.25.1)
Requires-Dist: requests-mock (>=1.9.3)
